{
    "plain": {
        "dist": {
            "average": 139979, 
            "worst": 148129, 
            "best": 133819
        }, 
        "time": {
            "average": 21.02108, 
            "worst": 21.76795, 
            "best": 19.98908
        }, 
        "params": {
            "method_mutate": "MUTATION_SA", 
            "method_select": "SELECTION_RANK", 
            "method_initial_population": "INITIAL_POPULATION_RANDOM", 
            "chr": 40, 
            "method_cross": "CROSSOVER_OX", 
            "mr": 0.7, 
            "cr": 0.3
        }, 
        "generations": {
            "average": 61, 
            "worst": 61, 
            "best": 61
        }
    }, 
    "initial-pop-3": {
        "dist": {
            "average": 130301, 
            "worst": 139998, 
            "best": 122969
        }, 
        "time": {
            "average": 74.47465, 
            "worst": 80.78047, 
            "best": 65.52889
        }, 
        "params": {
            "method_mutate": "MUTATION_SA", 
            "method_select": "SELECTION_RANK", 
            "method_cross": "CROSSOVER_OX", 
            "method_initial_population": "INITIAL_POPULATION_SEMIACS", 
            "chr": 40, 
            "initial_ants": 3, 
            "mr": 0.7, 
            "cr": 0.3
        }, 
        "generations": {
            "average": 61, 
            "worst": 61, 
            "best": 61
        }
    }, 
    "initial-pop-22": {
        "dist": {
            "average": 129738, 
            "worst": 138134, 
            "best": 121378
        }, 
        "time": {
            "average": 534.33684, 
            "worst": 557.07511, 
            "best": 509.44128
        }, 
        "params": {
            "method_mutate": "MUTATION_SA", 
            "method_select": "SELECTION_RANK", 
            "method_initial_population": "INITIAL_POPULATION_SEMIACS", 
            "chr": 40, 
            "method_cross": "CROSSOVER_OX", 
            "initial_ants": 22, 
            "mr": 0.7, 
            "cr": 0.3
        }, 
        "generations": {
            "average": 61, 
            "worst": 61, 
            "best": 61
        }
    }, 
    "initial-pop-44": {
        "dist": {
            "average": 126618, 
            "worst": 135549, 
            "best": 118604
        }, 
        "time": {
            "average": 1138.0624, 
            "worst": 1610.34788, 
            "best": 994.93578
        }, 
        "params": {
            "method_mutate": "MUTATION_SA", 
            "method_select": "SELECTION_RANK", 
            "method_initial_population": "INITIAL_POPULATION_SEMIACS", 
            "chr": 40, 
            "method_cross": "CROSSOVER_OX", 
            "initial_ants": 44, 
            "mr": 0.7, 
            "cr": 0.3
        }, 
        "generations": {
            "average": 61, 
            "worst": 61, 
            "best": 61
        }
    }, 
    "initial-pop-32": {
        "dist": {
            "average": 128747, 
            "worst": 137427, 
            "best": 121084
        }, 
        "time": {
            "average": 762.18672, 
            "worst": 805.46655, 
            "best": 701.9873
        }, 
        "params": {
            "method_mutate": "MUTATION_SA", 
            "method_select": "SELECTION_RANK", 
            "method_initial_population": "INITIAL_POPULATION_SEMIACS", 
            "chr": 40, 
            "method_cross": "CROSSOVER_OX", 
            "initial_ants": 32, 
            "mr": 0.7, 
            "cr": 0.3
        }, 
        "generations": {
            "average": 61, 
            "worst": 61, 
            "best": 61
        }
    }, 
    "initial-pop-11": {
        "dist": {
            "average": 131395, 
            "worst": 142051, 
            "best": 122981
        }, 
        "time": {
            "average": 262.16049, 
            "worst": 282.89331, 
            "best": 248.59492
        }, 
        "params": {
            "method_mutate": "MUTATION_SA", 
            "method_select": "SELECTION_RANK", 
            "method_initial_population": "INITIAL_POPULATION_SEMIACS", 
            "chr": 40, 
            "method_cross": "CROSSOVER_OX", 
            "initial_ants": 11, 
            "mr": 0.7, 
            "cr": 0.3
        }, 
        "generations": {
            "average": 61, 
            "worst": 61, 
            "best": 61
        }
    }, 
    "initial-pop-55": {
        "dist": {
            "average": 138369, 
            "worst": 157703, 
            "best": 121889
        }, 
        "time": {
            "average": 1727.54606, 
            "worst": 2288.49372, 
            "best": 1418.59683
        }, 
        "params": {
            "method_mutate": "MUTATION_SA", 
            "method_select": "SELECTION_RANK", 
            "method_initial_population": "INITIAL_POPULATION_SEMIACS", 
            "chr": 40, 
            "method_cross": "CROSSOVER_OX", 
            "initial_ants": 55, 
            "mr": 0.7, 
            "cr": 0.3
        }, 
        "generations": {
            "average": 37, 
            "worst": 61, 
            "best": 1
        }
    }
}